cs/range.py
cs.range-20230701.dist-info/METADATA
cs.range-20230701.dist-info/WHEEL
cs.range-20230701.dist-info/top_level.txt
cs.range-20230701.dist-info/RECORD
